{
  "单据种类": "销货合同",
  "合同号": "MY24069",
  "日期": "2024.04.16",
  "卖方信息":{
    "公司名称": "晋裕国际贸易发展有限公司",
    "地址": "佛山顺德",
    "电话": "00852-25668109",
    "传真": "00852-22345811"
  },
  "买方信息": {
    "公司名称": "苏州精实电子科技有限公司",
    "地址": "",
    "电话": "",
    "传真": "0512-85166666"
  },
  "商品信息": [
    {
      "商品名称": "PET薄膜",
      "数量": "7560平方米",
      "单价": "3.6239",
      "总价": "27,396.69"
    },
    {
      "商品名称": "PET薄膜",
      "数量": "1760平方米",
      "单价": "3.6239",
      "总价": "6,378.07"
    },
    {
      "商品名称": "PET薄膜",
      "数量": "16380平方米",
      "单价": "3.6239",
      "总价": "59,359.48"
    },
    {
      "商品名称": "PET薄膜",
      "数量": "840平方米",
      "单价": "7.4735",
      "总价": "6,277.74"
    },
    {
      "商品名称": "PET薄膜",
      "数量": "440平方米",
      "单价": "6.9700",
      "总价": "3,066.80"
    }
  ],
  "商品总数量": "26980平方米",
  "商品总价格": "102,478.78"
}